dinov2_retrieval/__init__.py
dinov2_retrieval/image_retriever.py
dinov2_retrieval-0.0.2.dist-info/METADATA
dinov2_retrieval-0.0.2.dist-info/WHEEL
dinov2_retrieval-0.0.2.dist-info/entry_points.txt
dinov2_retrieval-0.0.2.dist-info/licenses/LICENSE
dinov2_retrieval-0.0.2.dist-info/RECORD
